circuitbreaker.py
circuitbreaker-2.1.0.dist-info/LICENSE.rst
circuitbreaker-2.1.0.dist-info/METADATA
circuitbreaker-2.1.0.dist-info/WHEEL
circuitbreaker-2.1.0.dist-info/top_level.txt
circuitbreaker-2.1.0.dist-info/RECORD
