Metadata-Version: 2.2
Name: circuitbreaker
Version: 2.1.0
Summary: Python Circuit Breaker pattern implementation
Home-page: https://github.com/fabfuel/circuitbreaker
Author: Fabian Fuelling
Author-email: pypi@fabfuel.de
License: BSD-3-Clause
Platform: any
Classifier: Intended Audience :: Developers
Classifier: License :: OSI Approved :: BSD License
Classifier: Operating System :: POSIX
Classifier: Operating System :: MacOS
Classifier: Operating System :: Unix
Classifier: Programming Language :: Python
Classifier: Programming Language :: Python :: 3
License-File: LICENSE.rst
Dynamic: author
Dynamic: author-email
Dynamic: classifier
Dynamic: description
Dynamic: home-page
Dynamic: license
Dynamic: platform
Dynamic: summary
